reconplogger.py
reconplogger_tests.py
reconplogger-4.18.0.dist-info/licenses/LICENSE.rst
reconplogger-4.18.0.dist-info/METADATA
reconplogger-4.18.0.dist-info/WHEEL
reconplogger-4.18.0.dist-info/top_level.txt
reconplogger-4.18.0.dist-info/RECORD
