Metadata-Version: 2.4
Name: reconplogger
Version: 4.18.0
Summary: omni:us python logging package
Author-email: Mauricio Villegas <mauricio@omnius.com>
License: The MIT License (MIT)
Project-URL: Documentation-stable, https://reconplogger.readthedocs.io/en/stable/
Project-URL: Documentation-latest, https://reconplogger.readthedocs.io/en/latest/
Project-URL: GitHub, https://github.com/omni-us/reconplogger
Project-URL: PyPI, https://pypi.org/project/reconplogger
Project-URL: Codecov, https://codecov.io/gh/omni-us/reconplogger
Platform: Any
Classifier: Development Status :: 5 - Production/Stable
Classifier: Programming Language :: Python
Classifier: Programming Language :: Python :: 3
Classifier: Programming Language :: Python :: 3 :: Only
Classifier: Programming Language :: Python :: 3.9
Classifier: Programming Language :: Python :: 3.10
Classifier: Programming Language :: Python :: 3.11
Classifier: Programming Language :: Python :: 3.12
Classifier: Programming Language :: Python :: 3.13
Classifier: Intended Audience :: Developers
Classifier: License :: OSI Approved :: MIT License
Classifier: Operating System :: POSIX :: Linux
Classifier: Operating System :: MacOS
Classifier: Operating System :: Microsoft :: Windows
Requires-Python: >=3.9
License-File: LICENSE.rst
Requires-Dist: python-json-logger>=3.2.1
Requires-Dist: PyYAML>=3.13
Provides-Extra: all
Requires-Dist: Flask>=1.1.1; extra == "all"
Requires-Dist: requests>=2.24.0; extra == "all"
Provides-Extra: test
Requires-Dist: pytest>=6.2.5; extra == "test"
Requires-Dist: pytest-cov>=4.0.0; extra == "test"
Requires-Dist: testfixtures==6.10.0; extra == "test"
Provides-Extra: dev
Requires-Dist: reconplogger[all]; extra == "dev"
Requires-Dist: reconplogger[test]; extra == "dev"
Requires-Dist: pre-commit>=2.19.0; extra == "dev"
Requires-Dist: tox>=3.25.0; extra == "dev"
Provides-Extra: doc
Requires-Dist: Sphinx>=1.7.9; extra == "doc"
Requires-Dist: sphinx-rtd-theme>=0.4.3; extra == "doc"
Requires-Dist: autodocsumm>=0.1.10; extra == "doc"
Requires-Dist: sphinx-autodoc-typehints>=1.11.1; extra == "doc"
Provides-Extra: maintainer
Requires-Dist: bump2version>=0.5.11; extra == "maintainer"
Requires-Dist: twine>=3.1.1; extra == "maintainer"
Dynamic: license-file
